masz/__init__.py
masz/client.py
masz/console.py
masz/discord_api.py
masz/masz_guild.py
masz/masz_modcase.py
masz/masz_motd.py
masz/masz_request.py
masz/masz_usermap.py
masz/masz_usernote.py
masz/request_adapter.py
masz/exceptions/__init__.py
masz/exceptions/base_exception.py
masz/exceptions/invalid_response.py
masz/exceptions/login_failure.py
masz/exceptions/request_failure.py
masz/helpers/__init__.py
masz/helpers/better_dateparser.py
masz/helpers/better_enum.py
masz/obj/__init__.py
masz/obj/adminstats.py
masz/obj/app_user.py
masz/obj/channel.py
masz/obj/comment.py
masz/obj/creation_type.py
masz/obj/discord_user.py
masz/obj/guild.py
masz/obj/guildconfig.py
masz/obj/member.py
masz/obj/modcase.py
masz/obj/motd.py
masz/obj/punishment_type.py
masz/obj/role.py
masz/obj/status.py
masz/obj/usermap.py
masz/obj/usernote.py
masz/obj/version.py
masz-1.2.3.dist-info/LICENSE
masz-1.2.3.dist-info/METADATA
masz-1.2.3.dist-info/WHEEL
masz-1.2.3.dist-info/top_level.txt
masz-1.2.3.dist-info/RECORD
