Metadata-Version: 2.1
Name: masz
Version: 1.2.3
Summary: API Wrapper for MASZ (A discord moderation bot)
Home-page: https://github.com/zaanposni/masz-api-wrapper
Author: zaanposni
Author-email: me@zaanposni.com
License: MIT
Keywords: MASZ,API,DISCORD,WRAPPER,JSON,REST,MODERATION,TOKEN,PYTHON
Platform: UNKNOWN
Classifier: Development Status :: 4 - Beta
Classifier: Intended Audience :: Developers
Classifier: Topic :: Software Development :: Build Tools
Classifier: License :: OSI Approved :: MIT License
Classifier: Programming Language :: Python :: 3
Classifier: Programming Language :: Python :: 3.6
Classifier: Programming Language :: Python :: 3.7
Classifier: Programming Language :: Python :: 3.8
Classifier: Programming Language :: Python :: 3.9
Requires-Dist: requests
Requires-Dist: typing
Requires-Dist: dateparser
Requires-Dist: rich
